<data>
    <reg>
        <visit_id>zj124</visit_id>
        <patient_type>2</patient_type>
        <org_code>100010</org_code>
        <system_source>1</system_source>
        <org_name>医院</org_name>
        <patient_no></patient_no>
        <patient_id>hs123455</patient_id>
        <visit_no>mz123</visit_no>
        <patient_name>患者</patient_name>
        <patient_name_spell>py</patient_name_spell>
        <height></height>
        <weight></weight>
        <gender_code>1</gender_code>
        <gender_name>男</gender_name>
        <idcard_type_code></idcard_type_code>
        <idcard_type_name></idcard_type_name>
        <idcard_no>510211198011290451</idcard_no>
        <med_card_no></med_card_no>
        <other_card_no></other_card_no>
        <health_file_no>266852156921821921</health_file_no>
        <health_card_no>959118462</health_card_no>
        <birthday>2000-12-30 01:00:00</birthday>
        <age>1.0</age>
        <age_unit>1</age_unit>
        <med_type_code>01</med_type_code>
        <med_type_name>商业保险</med_type_name>
        <occupation_code>13</occupation_code>
        <occupation_name>专业技术人员</occupation_name>
        <edu_code></edu_code>
        <edu_name></edu_name>
        <marriage_code>10</marriage_code>
        <marriage_name>未婚</marriage_name>
        <blood_abo_code></blood_abo_code>
        <blood_rh_code></blood_rh_code>
        <present_address>现住址</present_address>
        <present_province></present_province>
        <present_city></present_city>
        <present_country></present_country>
        <present_town></present_town>
        <present_street></present_street>
        <present_house></present_house>
        <present_post_code></present_post_code>
        <mobile_phone></mobile_phone>
        <email></email>
        <telphone>13200568911</telphone>
        <work_unit_code></work_unit_code>
        <work_unit_name>人民大学</work_unit_name>
        <work_unit_phone>023-89282251</work_unit_phone>
        <work_unit_address></work_unit_address>
        <work_addr_province></work_addr_province>
        <work_addr_city></work_addr_city>
        <work_addr_country></work_addr_country>
        <work_addr_town></work_addr_town>
        <work_addr_street></work_addr_street>
        <work_addr_house></work_addr_house>
        <work_post_code></work_post_code>
        <contact_name>联系人</contact_name>
        <contact_relation_code></contact_relation_code>
        <contact_relation_name></contact_relation_name>
        <contact_gender_code></contact_gender_code>
        <contact_phone>12345678</contact_phone>
        <contact_post_code>400010</contact_post_code>
        <contact_address>地址</contact_address>
        <contact_addr_province>省</contact_addr_province>
        <contact_addr_city>市</contact_addr_city>
        <contact_addr_country>县</contact_addr_country>
        <contact_addr_town>乡</contact_addr_town>
        <contact_addr_street>村</contact_addr_street>
        <contact_addr_house>258</contact_addr_house>
        <residence_address></residence_address>
        <residence_province></residence_province>
        <residence_city></residence_city>
        <residence_country></residence_country>
        <residence_town></residence_town>
        <residence_street></residence_street>
        <residence_house></residence_house>
        <residence_post_code></residence_post_code>
        <birth_address>重庆</birth_address>
        <birth_province></birth_province>
        <birth_city></birth_city>
        <birth_country></birth_country>
        <birth_town></birth_town>
        <birth_street></birth_street>
        <birth_house></birth_house>
        <nationality_code>01</nationality_code>
        <nationality_name>中国</nationality_name>
        <nation_code>01</nation_code>
        <nation_name>汉族</nation_name>
        <potl_code></potl_code>
        <spcl_code></spcl_code>
        <hometown_code></hometown_code>
        <hometown_name></hometown_name>
        <hometown_address></hometown_address>
        <hometown_province></hometown_province>
        <hometown_city></hometown_city>
        <hometown_city_code></hometown_city_code>
        <hometown_country></hometown_country>
        <hometown_town></hometown_town>
        <hometown_street></hometown_street>
        <hometown_house></hometown_house>
        <guardian_idcard_type></guardian_idcard_type>
        <guardian_idcard></guardian_idcard>
        <guardian_name></guardian_name>
        <guardian_gender_code></guardian_gender_code>
        <guardian_contact_way></guardian_contact_way>
        <guardian_birthday></guardian_birthday>
        <guardian_idcard_expire_date></guardian_idcard_expire_date>
        <archiving_staff_no>95626</archiving_staff_no>
        <archiving_staff_name>马蒙</archiving_staff_name>
        <mother_idcard_no></mother_idcard_no>
        <mother_name></mother_name>
        <medical_history></medical_history>
        <infectious_history></infectious_history>
        <vaccination_history></vaccination_history>
        <operation_history></operation_history>
        <blood_history></blood_history>
        <allergy_history></allergy_history>
        <personal_history></personal_history>
        <obstetrical_history></obstetrical_history>
        <menstrual_history></menstrual_history>
        <family_history></family_history>
        <present_history></present_history>
        <past_history></past_history>
        <death_flag></death_flag>
        <death_date></death_date>
        <hosp_card_no></hosp_card_no>
    </reg>
</data>
